{
  "scenario_name": "EV Wars Extended (2017-2020)",
  "description": "16 Quarters of EV Disruption. Tesla's Model 3 ramp-up vs GM's Bolt.",
  "turns_data": [
    { "turn": 1, "note": "2017 Q1", "companies": { "Tesla": { "inputs": { "price": 55000, "marketing_spend_ratio": 0.00, "rd_spend_ratio": 0.15 }, "outputs": { "actual_market_share": 0.25 } }, "GM": { "inputs": { "price": 37000, "marketing_spend_ratio": 0.05, "rd_spend_ratio": 0.04 }, "outputs": { "actual_market_share": 0.20 } } } },
    { "turn": 2, "note": "2017 Q2", "companies": { "Tesla": { "inputs": { "price": 55000, "marketing_spend_ratio": 0.00, "rd_spend_ratio": 0.16 }, "outputs": { "actual_market_share": 0.28 } }, "GM": { "inputs": { "price": 37000, "marketing_spend_ratio": 0.05, "rd_spend_ratio": 0.04 }, "outputs": { "actual_market_share": 0.18 } } } },
    { "turn": 3, "note": "2017 Q3: Model 3 Production Hell", "companies": { "Tesla": { "inputs": { "price": 55000, "marketing_spend_ratio": 0.00, "rd_spend_ratio": 0.18 }, "outputs": { "actual_market_share": 0.30 } }, "GM": { "inputs": { "price": 37000, "marketing_spend_ratio": 0.06, "rd_spend_ratio": 0.04 }, "outputs": { "actual_market_share": 0.17 } } } },
    { "turn": 4, "note": "2017 Q4", "companies": { "Tesla": { "inputs": { "price": 54000, "marketing_spend_ratio": 0.00, "rd_spend_ratio": 0.18 }, "outputs": { "actual_market_share": 0.35 } }, "GM": { "inputs": { "price": 36500, "marketing_spend_ratio": 0.06, "rd_spend_ratio": 0.04 }, "outputs": { "actual_market_share": 0.16 } } } },
    { "turn": 5, "note": "2018 Q1", "companies": { "Tesla": { "inputs": { "price": 53000, "marketing_spend_ratio": 0.00, "rd_spend_ratio": 0.17 }, "outputs": { "actual_market_share": 0.40 } }, "GM": { "inputs": { "price": 36500, "marketing_spend_ratio": 0.05, "rd_spend_ratio": 0.04 }, "outputs": { "actual_market_share": 0.15 } } } },
    { "turn": 6, "note": "2018 Q2: Production stabilized", "companies": { "Tesla": { "inputs": { "price": 52000, "marketing_spend_ratio": 0.00, "rd_spend_ratio": 0.15 }, "outputs": { "actual_market_share": 0.45 } }, "GM": { "inputs": { "price": 36000, "marketing_spend_ratio": 0.06, "rd_spend_ratio": 0.04 }, "outputs": { "actual_market_share": 0.14 } } } },
    { "turn": 7, "note": "2018 Q3: Profitability attained", "companies": { "Tesla": { "inputs": { "price": 51000, "marketing_spend_ratio": 0.00, "rd_spend_ratio": 0.14 }, "outputs": { "actual_market_share": 0.50 } }, "GM": { "inputs": { "price": 36000, "marketing_spend_ratio": 0.06, "rd_spend_ratio": 0.04 }, "outputs": { "actual_market_share": 0.13 } } } },
    { "turn": 8, "note": "2018 Q4", "companies": { "Tesla": { "inputs": { "price": 50000, "marketing_spend_ratio": 0.00, "rd_spend_ratio": 0.13 }, "outputs": { "actual_market_share": 0.55 } }, "GM": { "inputs": { "price": 36000, "marketing_spend_ratio": 0.07, "rd_spend_ratio": 0.04 }, "outputs": { "actual_market_share": 0.12 } } } },
    { "turn": 9, "note": "2019 Q1", "companies": { "Tesla": { "inputs": { "price": 49000, "marketing_spend_ratio": 0.00, "rd_spend_ratio": 0.12 }, "outputs": { "actual_market_share": 0.58 } }, "GM": { "inputs": { "price": 35000, "marketing_spend_ratio": 0.07, "rd_spend_ratio": 0.04 }, "outputs": { "actual_market_share": 0.11 } } } },
    { "turn": 10, "note": "2019 Q2", "companies": { "Tesla": { "inputs": { "price": 48000, "marketing_spend_ratio": 0.00, "rd_spend_ratio": 0.12 }, "outputs": { "actual_market_share": 0.60 } }, "GM": { "inputs": { "price": 35000, "marketing_spend_ratio": 0.07, "rd_spend_ratio": 0.04 }, "outputs": { "actual_market_share": 0.10 } } } },
    { "turn": 11, "note": "2019 Q3", "companies": { "Tesla": { "inputs": { "price": 47000, "marketing_spend_ratio": 0.00, "rd_spend_ratio": 0.11 }, "outputs": { "actual_market_share": 0.62 } }, "GM": { "inputs": { "price": 35000, "marketing_spend_ratio": 0.07, "rd_spend_ratio": 0.04 }, "outputs": { "actual_market_share": 0.09 } } } },
    { "turn": 12, "note": "2019 Q4", "companies": { "Tesla": { "inputs": { "price": 46000, "marketing_spend_ratio": 0.00, "rd_spend_ratio": 0.11 }, "outputs": { "actual_market_share": 0.65 } }, "GM": { "inputs": { "price": 35000, "marketing_spend_ratio": 0.08, "rd_spend_ratio": 0.04 }, "outputs": { "actual_market_share": 0.08 } } } },
    { "turn": 13, "note": "2020 Q1: Dominance", "companies": { "Tesla": { "inputs": { "price": 45000, "marketing_spend_ratio": 0.00, "rd_spend_ratio": 0.10 }, "outputs": { "actual_market_share": 0.68 } }, "GM": { "inputs": { "price": 35000, "marketing_spend_ratio": 0.08, "rd_spend_ratio": 0.04 }, "outputs": { "actual_market_share": 0.07 } } } },
    { "turn": 14, "note": "2020 Q2", "companies": { "Tesla": { "inputs": { "price": 44000, "marketing_spend_ratio": 0.00, "rd_spend_ratio": 0.10 }, "outputs": { "actual_market_share": 0.70 } }, "GM": { "inputs": { "price": 34000, "marketing_spend_ratio": 0.08, "rd_spend_ratio": 0.04 }, "outputs": { "actual_market_share": 0.06 } } } },
    { "turn": 15, "note": "2020 Q3", "companies": { "Tesla": { "inputs": { "price": 43000, "marketing_spend_ratio": 0.00, "rd_spend_ratio": 0.10 }, "outputs": { "actual_market_share": 0.72 } }, "GM": { "inputs": { "price": 34000, "marketing_spend_ratio": 0.08, "rd_spend_ratio": 0.04 }, "outputs": { "actual_market_share": 0.06 } } } },
    { "turn": 16, "note": "2020 Q4", "companies": { "Tesla": { "inputs": { "price": 42000, "marketing_spend_ratio": 0.00, "rd_spend_ratio": 0.10 }, "outputs": { "actual_market_share": 0.75 } }, "GM": { "inputs": { "price": 33000, "marketing_spend_ratio": 0.08, "rd_spend_ratio": 0.04 }, "outputs": { "actual_market_share": 0.05 } } } }
  ]
}